{
    "schema" :
    {
        "attributes":[
            {
                "name":"id",
                "type":"int",
                "length":11,
                "null":0,
                "auto_increment":1
            },
            {
                "name":"id_slider",
                "type":"int",
                "length":11,
                "null":0
            },
            {
                "name":"tipo",
                "type":"varchar",
                "length":50,
                "null":0,
                "default":""
            },
            {
                "name":"file",
                "type":"varchar",
                "length":255,
                "null":1,
                "default":""
            },
            {
                "name":"titulo",
                "type":"varchar",
                "length":255,
                "null":1,
                "default":""
            },
            {
                "name":"descripcion",
                "type":"text",
                "null":1,
                "default":""
            },
            {
                "name":"url",
                "type":"varchar",
                "length":255,
                "null":1,
                "default":""
            },
            {
                "name":"createdAt",
                "type":"datetime",
                "null":0
            },
            {
                "name":"updateAt",
                "type":"datetime",
                "null":1
            },
            {
                "name":"status",
                "type":"int",
                "length":1,
                "null":0
            },
            {
                "name":"file_responsive",
                "type":"varchar",
                "length":255,
                "null":1,
                "default":""
            },
            {
                "name":"code",
                "type":"text",
                "null":1,
                "default":""
            },
            {
                "name":"orden",
                "type":"int",
                "length":11,
                "null":1,
                "default":0
            },
            {
                "name":"boton_link",
                "type":"int",
                "length":11,
                "null":1,
                "default":0
            },
            {
                "name":"fecha_inicio",
                "type":"date",
                "null":1
            },
            {
                "name":"fecha_fin",
                "type":"date",
                "null":1
            }

        ],
        "config":{
            "primary":"id",
            "engine":"InnoDB",
            "keys":
            {
                "sliders_sliders" : {
                    "foreing" : "id",
                    "local":"id_slider",
                    "delete":"NO ACTION",
                    "update":"NO ACTION"
                }
            }
        }
    }
    ,
    "data":[]
}